odoo/addons/crm_secondary_salesperson/README.rst
odoo/addons/crm_secondary_salesperson/__init__.py
odoo/addons/crm_secondary_salesperson/__manifest__.py
odoo/addons/crm_secondary_salesperson/i18n/crm_secondary_salesperson.pot
odoo/addons/crm_secondary_salesperson/i18n/es.po
odoo/addons/crm_secondary_salesperson/i18n/pt_BR.po
odoo/addons/crm_secondary_salesperson/models/__init__.py
odoo/addons/crm_secondary_salesperson/models/crm_lead.py
odoo/addons/crm_secondary_salesperson/readme/CONFIGURE.rst
odoo/addons/crm_secondary_salesperson/readme/CONTRIBUTORS.rst
odoo/addons/crm_secondary_salesperson/readme/DESCRIPTION.rst
odoo/addons/crm_secondary_salesperson/readme/USAGE.rst
odoo/addons/crm_secondary_salesperson/static/description/banner.png
odoo/addons/crm_secondary_salesperson/static/description/icon.png
odoo/addons/crm_secondary_salesperson/static/description/index.html
odoo/addons/crm_secondary_salesperson/views/crm_lead.xml
odoo12_addon_crm_secondary_salesperson-12.0.1.0.2.dist-info/METADATA
odoo12_addon_crm_secondary_salesperson-12.0.1.0.2.dist-info/WHEEL
odoo12_addon_crm_secondary_salesperson-12.0.1.0.2.dist-info/top_level.txt
odoo12_addon_crm_secondary_salesperson-12.0.1.0.2.dist-info/RECORD
